Component-Modules/sync_sram/sync_sram.sv
module sync_sram (
    // Normal memory interface
    input   logic           clk,
    input   logic           chip_enable,
    input   logic           write_enable,
    input   logic [4:0]     addr,
    input   logic [31:0]    data_in,
    output  logic [31:0]    data_out,

    // Initialization interface
    input   logic           init_en,
    input   logic [4:0]     init_addr,
    input   logic [31:0]    init_data,
    input   logic           init_we
);

    logic [31:0] memory [0:31];

    always_ff @(posedge clk) begin
        // Initialization has priority
        if (init_en && init_we) begin
            memory[init_addr] <= init_data;
        end
        // Normal memory operation
        else if (chip_enable) begin
            if (write_enable) begin
                memory[addr] <= data_in;
            end
        end
    end
    
    // Combinational read (immediate)
    always_comb begin
        if (chip_enable && !write_enable) begin
            data_out = memory[addr];
        end else begin
            data_out = 'x;
        end
    end
endmodule

Component-Modules/sync_sram/sync_sram_tb.sv
`timescale 1ns/1ps

module sync_sram_tb;

    // Testbench parameters
    localparam CLK_PERIOD = 10;  // 100 MHz clock
    localparam TEST_DEPTH = 32;  // Test all 32 addresses
    
    // DUT signals
    logic           clk;
    logic           chip_enable;
    logic           write_enable;
    logic [4:0]     addr;
    logic [31:0]    data_in;
    logic [31:0]    data_out;
    
    logic           init_en;
    logic [4:0]     init_addr;
    logic [31:0]    init_data;
    logic           init_we;
    
    // Testbench variables
    logic [31:0] memory_model [0:31];  // Reference model
    int test_count = 0;
    int error_count = 0;
    
    // Instantiate DUT
    sync_sram dut (
        .clk          (clk),
        .chip_enable  (chip_enable),
        .write_enable (write_enable),
        .addr         (addr),
        .data_in      (data_in),
        .data_out     (data_out),
        .init_en      (init_en),
        .init_addr    (init_addr),
        .init_data    (init_data),
        .init_we      (init_we)
    );
    
    // Clock generation
    initial begin
        clk = 0;
        forever #(CLK_PERIOD/2) clk = ~clk;
    end
    
    // Initialize signals
    task automatic init_signals;
        chip_enable = 0;
        write_enable = 0;
        addr = 0;
        data_in = 0;
        init_en = 0;
        init_addr = 0;
        init_data = 0;
        init_we = 0;
        
        // Initialize reference model
        for (int i = 0; i < 32; i++) begin
            memory_model[i] = 32'hXXXXXXXX;  // Unknown state
        end
    endtask
    
    // Wait for N clock cycles
    task automatic wait_cycles(input int cycles);
        repeat (cycles) @(posedge clk);
    endtask
    
    // Initialize memory using init interface
    task automatic init_memory(
        input logic [4:0] init_addr_i,
        input logic [31:0] init_data_i
    );
        @(negedge clk);  // Setup before clock edge
        init_en = 1;
        init_we = 1;
        init_addr = init_addr_i;
        init_data = init_data_i;
        
        @(posedge clk);  // Write happens here
        #1;  // Small delay for propagation
        
        init_en = 0;
        init_we = 0;
        
        // Update reference model
        memory_model[init_addr_i] = init_data_i;
        
        $display("[%0t] INIT: Addr=%0d, Data=0x%08h", $time, init_addr_i, init_data_i);
        wait_cycles(1);
    endtask
    
    // Write to memory using normal interface
    task automatic write_memory(
        input logic [4:0] addr_i,
        input logic [31:0] data_i
    );
        @(negedge clk);  // Setup before clock edge
        chip_enable = 1;
        write_enable = 1;
        addr = addr_i;
        data_in = data_i;
        
        @(posedge clk);  // Write happens here
        #1;  // Small delay for propagation
        
        chip_enable = 1;
        write_enable = 0;
        
        // Update reference model
        memory_model[addr_i] = data_i;
        
        $display("[%0t] WRITE: Addr=%0d, Data=0x%08h", $time, addr_i, data_i);
        wait_cycles(1);
    endtask
    
    // Read from memory and verify (COMBINATIONAL - immediate)
    task automatic read_and_verify(
        input logic [4:0] addr_i,
        input logic [31:0] expected_data_i = 'x
    );
        logic [31:0] ref_data;
        
        @(negedge clk);  // Setup before clock edge
        chip_enable = 1;
        write_enable = 0;
        addr = addr_i;
        
        #1;  // Small delay for combinational logic
        
        // Get expected data from reference model
        ref_data = memory_model[addr_i];
        
        // Override with explicit expected value if provided
        if (expected_data_i !== 'x) begin
            ref_data = expected_data_i;
        end
        
        // Verify the data (data_out should be available immediately)
        if (data_out === ref_data) begin
            $display("[%0t] READ:  Addr=%0d, Data=0x%08h ✓", $time, addr_i, data_out);
        end else begin
            $error("[%0t] READ:  Addr=%0d, Expected=0x%08h, Got=0x%08h ✗", 
                   $time, addr_i, ref_data, data_out);
            error_count++;
        end
        
        @(posedge clk);  // Align to clock edge
        chip_enable = 1;
        
        test_count++;
        wait_cycles(1);
    endtask
    
    // Test 1: Basic initialization test
    task automatic test_initialization;
        $display("\n=== Test 1: Initialization Interface Test ===");
        
        // Initialize some locations
        init_memory(5'd0,  32'hDEADBEEF);
        init_memory(5'd1,  32'hCAFEBABE);
        init_memory(5'd31, 32'h12345678);
        
        // Verify initialization (check immediately after write)
        read_and_verify(5'd0);   // Should be 0xDEADBEEF
        read_and_verify(5'd1);   // Should be 0xCAFEBABE  
        read_and_verify(5'd31);  // Should be 0x12345678
        
        // Check uninitialized location (should be X)
        read_and_verify(5'd10);
    endtask
    
    // Test 2: Normal read/write test
    task automatic test_read_write;
        $display("\n=== Test 2: Normal Read/Write Test ===");
        
        // Write using normal interface
        write_memory(5'd2,  32'hA5A5A5A5);
        write_memory(5'd3,  32'h5A5A5A5A);
        write_memory(5'd4,  32'hFFFFFFFF);
        
        // Read back (immediate verification)
        read_and_verify(5'd2);  // Should be 0xA5A5A5A5
        read_and_verify(5'd3);  // Should be 0x5A5A5A5A
        read_and_verify(5'd4);  // Should be 0xFFFFFFFF
    endtask
    
    // Test 3: Priority test (init vs normal)
    task automatic test_priority;
        $display("\n=== Test 3: Priority Test (Init > Normal) ===");
        
        // Write to address 5 using normal interface
        write_memory(5'd5, 32'h11111111);
        read_and_verify(5'd5);  // Should be 0x11111111
        
        // Simultaneously try normal write and init write (init should win)
        @(negedge clk);
        chip_enable = 1;
        write_enable = 1;
        addr = 5'd5;
        data_in = 32'h22222222;  // This should be ignored
        
        init_en = 1;
        init_we = 1;
        init_addr = 5'd5;
        init_data = 32'h33333333;  // This should be written
        
        @(posedge clk);
        #1;
        chip_enable = 1;
        write_enable = 0;
        init_en = 0;
        init_we = 0;
        
        // Update reference model for init write
        memory_model[5'd5] = 32'h33333333;
        
        // Verify init write took priority
        read_and_verify(5'd5);  // Should be 0x33333333
    endtask
    
    // Test 4: Immediate read-after-write test
    task automatic test_immediate_read;
        $display("\n=== Test 4: Immediate Read-After-Write ===");
        
        // Write and read same address in same cycle
        @(negedge clk);
        chip_enable = 1;
        write_enable = 1;
        addr = 5'd9;
        data_in = 32'h99999999;
        
        @(posedge clk);
        #1;
        
        // Immediately read same address (combinational output should show new data)
        write_enable = 0;
        #1;
        
        if (data_out === 32'h99999999) begin
            $display("[%0t] IMMEDIATE READ: Addr=9, Data=0x%08h ✓", $time, data_out);
        end else begin
            $error("[%0t] IMMEDIATE READ: Expected 0x99999999, Got 0x%08h ✗", $time, data_out);
            error_count++;
        end
        
        chip_enable = 1;
        wait_cycles(1);
    endtask
    
    // Test 5: Full memory test
    task automatic test_full_memory;
        $display("\n=== Test 5: Full Memory Test ===");
        
        // Write pattern to all addresses
        for (int i = 0; i < TEST_DEPTH; i++) begin
            write_memory(i[4:0], {16'hFACE, i[15:0]});
        end
        
        // Read back all addresses (immediate verification)
        for (int i = 0; i < TEST_DEPTH; i++) begin
            read_and_verify(i[4:0], {16'hFACE, i[15:0]});
        end
    endtask
    
    // Test 6: Concurrent operations test
    task automatic test_concurrent;
        $display("\n=== Test 6: Concurrent Operations Test ===");
        
        // Initialize some data
        init_memory(5'd7, 32'h11111111);
        init_memory(5'd8, 32'h22222222);
        
        // Test changing address while reading
        @(negedge clk);
        chip_enable = 1;
        write_enable = 0;
        addr = 5'd7;  // Read address 7
        
        #5;  // Mid-cycle, change address
        addr = 5'd8;
        
        #5;  // Check data_out immediately reflects new address
        if (data_out === 32'h22222222) begin
            $display("[%0t] CONCURRENT: Addr=8, Data=0x%08h ✓", $time, data_out);
        end else begin
            $error("[%0t] CONCURRENT: Expected 0x22222222, Got 0x%08h ✗", $time, data_out);
            error_count++;
        end
        
        @(posedge clk);
        chip_enable = 1;
        wait_cycles(1);
    endtask
    
    // Main test sequence
    initial begin
        $display("\n=========================================");
        $display("     sync_sram Testbench Started");
        $display("=========================================");
        
        // Initialize
        init_signals();
        wait_cycles(2);
        
        // Run tests
        test_initialization();
        wait_cycles(2);
        
        test_read_write();
        wait_cycles(2);
        
        test_priority();
        wait_cycles(2);
        
        test_immediate_read();
        wait_cycles(2);
        
        test_full_memory();
        wait_cycles(2);
        
        test_concurrent();
        wait_cycles(2);
        
        // Summary
        $display("\n=========================================");
        $display("     Test Summary");
        $display("=========================================");
        $display("Total tests run: %0d", test_count);
        $display("Errors: %0d", error_count);
        
        if (error_count == 0) begin
            $display("\n✓ All tests PASSED!");
        end else begin
            $display("\n✗ %0d test(s) FAILED!", error_count);
        end
        
        $display("\nSimulation completed at time %0t ns", $time);
        $finish;
    end
    
    // Monitor for debugging
    initial begin
        forever @(negedge clk) begin
            if (chip_enable) begin
                $display("[%0t] MONITOR: addr=%0d, we=%b, data_in=0x%08h, data_out=0x%08h",
                        $time, addr, write_enable, data_in, data_out);
            end
        end
    end
    
    // Waveform dumping (for debugging)
    initial begin
        $dumpfile("sync_sram_tb.vcd");
        $dumpvars(0, sync_sram_tb);
    end
    
    // Timeout check
    initial begin
        #1000000;  // 1ms timeout
        $display("\n⏰ Simulation timeout!");
        $finish;
    end

endmodule

Component-Modules/sync_sram/sync_sram_tb.vcd
$date
	Fri Dec 05 23:11:36 2025
$end
$version
	ModelSim Version 10.5b
$end
$timescale
	1ps
$end

$scope module sync_sram_tb $end
$var parameter 32 ! CLK_PERIOD $end
$var parameter 32 " TEST_DEPTH $end
$var reg 1 # clk $end
$var reg 1 $ chip_enable $end
$var reg 1 % write_enable $end
$var reg 5 & addr [4:0] $end
$var reg 32 ' data_in [31:0] $end
$var reg 32 ( data_out [31:0] $end
$var reg 1 ) init_en $end
$var reg 5 * init_addr [4:0] $end
$var reg 32 + init_data [31:0] $end
$var reg 1 , init_we $end
$var integer 32 - test_count $end
$var integer 32 . error_count $end

$scope task init_signals $end
$upscope $end

$scope task wait_cycles $end
$upscope $end

$scope task init_memory $end
$upscope $end

$scope task write_memory $end
$upscope $end

$scope task read_and_verify $end
$upscope $end

$scope task test_initialization $end
$upscope $end

$scope task test_read_write $end
$upscope $end

$scope task test_priority $end
$upscope $end

$scope task test_immediate_read $end
$upscope $end

$scope task test_full_memory $end
$upscope $end

$scope task test_concurrent $end
$upscope $end

$scope module dut $end
$var wire 1 / clk $end
$var wire 1 0 chip_enable $end
$var wire 1 1 write_enable $end
$var wire 1 2 addr [4] $end
$var wire 1 3 addr [3] $end
$var wire 1 4 addr [2] $end
$var wire 1 5 addr [1] $end
$var wire 1 6 addr [0] $end
$var wire 1 7 data_in [31] $end
$var wire 1 8 data_in [30] $end
$var wire 1 9 data_in [29] $end
$var wire 1 : data_in [28] $end
$var wire 1 ; data_in [27] $end
$var wire 1 < data_in [26] $end
$var wire 1 = data_in [25] $end
$var wire 1 > data_in [24] $end
$var wire 1 ? data_in [23] $end
$var wire 1 @ data_in [22] $end
$var wire 1 A data_in [21] $end
$var wire 1 B data_in [20] $end
$var wire 1 C data_in [19] $end
$var wire 1 D data_in [18] $end
$var wire 1 E data_in [17] $end
$var wire 1 F data_in [16] $end
$var wire 1 G data_in [15] $end
$var wire 1 H data_in [14] $end
$var wire 1 I data_in [13] $end
$var wire 1 J data_in [12] $end
$var wire 1 K data_in [11] $end
$var wire 1 L data_in [10] $end
$var wire 1 M data_in [9] $end
$var wire 1 N data_in [8] $end
$var wire 1 O data_in [7] $end
$var wire 1 P data_in [6] $end
$var wire 1 Q data_in [5] $end
$var wire 1 R data_in [4] $end
$var wire 1 S data_in [3] $end
$var wire 1 T data_in [2] $end
$var wire 1 U data_in [1] $end
$var wire 1 V data_in [0] $end
$var reg 32 W data_out [31:0] $end
$var wire 1 X init_en $end
$var wire 1 Y init_addr [4] $end
$var wire 1 Z init_addr [3] $end
$var wire 1 [ init_addr [2] $end
$var wire 1 \ init_addr [1] $end
$var wire 1 ] init_addr [0] $end
$var wire 1 ^ init_data [31] $end
$var wire 1 _ init_data [30] $end
$var wire 1 ` init_data [29] $end
$var wire 1 a init_data [28] $end
$var wire 1 b init_data [27] $end
$var wire 1 c init_data [26] $end
$var wire 1 d init_data [25] $end
$var wire 1 e init_data [24] $end
$var wire 1 f init_data [23] $end
$var wire 1 g init_data [22] $end
$var wire 1 h init_data [21] $end
$var wire 1 i init_data [20] $end
$var wire 1 j init_data [19] $end
$var wire 1 k init_data [18] $end
$var wire 1 l init_data [17] $end
$var wire 1 m init_data [16] $end
$var wire 1 n init_data [15] $end
$var wire 1 o init_data [14] $end
$var wire 1 p init_data [13] $end
$var wire 1 q init_data [12] $end
$var wire 1 r init_data [11] $end
$var wire 1 s init_data [10] $end
$var wire 1 t init_data [9] $end
$var wire 1 u init_data [8] $end
$var wire 1 v init_data [7] $end
$var wire 1 w init_data [6] $end
$var wire 1 x init_data [5] $end
$var wire 1 y init_data [4] $end
$var wire 1 z init_data [3] $end
$var wire 1 { init_data [2] $end
$var wire 1 | init_data [1] $end
$var wire 1 } init_data [0] $end
$var wire 1 ~ init_we $end
$upscope $end
$upscope $end
$enddefinitions $end
#0
$dumpvars
0#
0$
0%
b0 &
b0 '
bx (
0)
b0 *
b0 +
0,
bx W
b1010 !
b100000 "
b0 -
b0 .
0/
00
01
06
05
04
03
02
0V
0U
0T
0S
0R
0Q
0P
0O
0N
0M
0L
0K
0J
0I
0H
0G
0F
0E
0D
0C
0B
0A
0@
0?
0>
0=
0<
0;
0:
09
08
07
0X
0]
0\
0[
0Z
0Y
0}
0|
0{
0z
0y
0x
0w
0v
0u
0t
0s
0r
0q
0p
0o
0n
0m
0l
0k
0j
0i
0h
0g
0f
0e
0d
0c
0b
0a
0`
0_
0^
0~
$end
#5000
1#
1/
#10000
0#
0/
#15000
1#
1/
#20000
0#
0/
1)
1,
b11011110101011011011111011101111 +
1X
1~
1}
1|
1{
1z
1x
1w
1v
1t
1s
1r
1q
1p
1n
1m
1k
1j
1h
1f
1d
1c
1b
1a
1_
1^
#25000
1#
1/
#26000
0)
0,
0X
0~
#30000
0#
0/
#35000
1#
1/
#40000
0#
0/
1)
1,
b1 *
b11001010111111101011101010111110 +
1X
1~
0}
1y
0w
0s
0m
1l
1i
1g
0c
0a
1]
#45000
1#
1/
#46000
0)
0,
0X
0~
#50000
0#
0/
#55000
1#
1/
#60000
0#
0/
1)
1,
b11111 *
b10010001101000101011001111000 +
1X
1~
0|
0{
1w
0v
1s
0r
0p
1o
0n
0l
0j
0g
0f
0b
1a
0_
0^
1\
1[
1Z
1Y
#65000
1#
1/
#66000
0)
0,
0X
0~
#70000
0#
0/
#75000
1#
1/
#80000
0#
0/
1$
10
b11011110101011011011111011101111 W
b11011110101011011011111011101111 (
#85000
1#
1/
b1 -
#90000
0#
0/
#95000
1#
1/
#100000
0#
0/
b1 &
16
b11001010111111101011101010111110 W
b11001010111111101011101010111110 (
#105000
1#
1/
b10 -
#110000
0#
0/
#115000
1#
1/
#120000
0#
0/
b11111 &
15
14
13
12
b10010001101000101011001111000 W
b10010001101000101011001111000 (
#125000
1#
1/
b11 -
#130000
0#
0/
#135000
1#
1/
#140000
0#
0/
b1010 &
06
04
02
bx W
bx (
#145000
1#
1/
b100 -
#150000
0#
0/
#155000
1#
1/
#160000
0#
0/
#165000
1#
1/
#170000
0#
0/
#175000
1#
1/
#180000
0#
0/
1%
b10 &
b10100101101001011010010110100101 '
1V
1T
1Q
1O
1N
1L
1I
1G
1F
1D
1A
1?
1>
1<
19
17
11
03
#185000
1#
1/
#186000
0%
01
b10100101101001011010010110100101 W
b10100101101001011010010110100101 (
#190000
0#
0/
#195000
1#
1/
#200000
0#
0/
1%
b11 &
b1011010010110100101101001011010 '
0V
1U
0T
1S
1R
0Q
1P
0O
0N
1M
0L
1K
1J
0I
1H
0G
0F
1E
0D
1C
1B
0A
1@
0?
0>
1=
0<
1;
1:
09
18
07
11
16
bx W
bx (
#205000
1#
1/
#206000
0%
01
b1011010010110100101101001011010 W
b1011010010110100101101001011010 (
#210000
0#
0/
#215000
1#
1/
#220000
0#
0/
1%
b100 &
b11111111111111111111111111111111 '
1V
1T
1Q
1O
1N
1L
1I
1G
1F
1D
1A
1?
1>
1<
19
17
11
06
05
14
bx W
bx (
#225000
1#
1/
#226000
0%
01
b11111111111111111111111111111111 W
b11111111111111111111111111111111 (
#230000
0#
0/
#235000
1#
1/
#240000
0#
0/
b10 &
15
04
b10100101101001011010010110100101 W
b10100101101001011010010110100101 (
#245000
1#
1/
b101 -
#250000
0#
0/
#255000
1#
1/
#260000
0#
0/
b11 &
16
b1011010010110100101101001011010 W
b1011010010110100101101001011010 (
#265000
1#
1/
b110 -
#270000
0#
0/
#275000
1#
1/
#280000
0#
0/
b100 &
06
05
14
b11111111111111111111111111111111 W
b11111111111111111111111111111111 (
#285000
1#
1/
b111 -
#290000
0#
0/
#295000
1#
1/
#300000
0#
0/
#305000
1#
1/
#310000
0#
0/
#315000
1#
1/
#320000
0#
0/
1%
b101 &
b10001000100010001000100010001 '
0U
0T
0S
0Q
0P
0O
0M
0L
0K
0I
0H
0G
0E
0D
0C
0A
0@
0?
0=
0<
0;
09
08
07
11
16
bx W
bx (
#325000
1#
1/
#326000
0%
01
b10001000100010001000100010001 W
b10001000100010001000100010001 (
#330000
0#
0/
#335000
1#
1/
#340000
0#
0/
#345000
1#
1/
b1000 -
#350000
0#
0/
#355000
1#
1/
#360000
0#
0/
1%
b100010001000100010001000100010 '
1)
1,
b101 *
b110011001100110011001100110011 +
1X
1~
1}
1|
0z
0w
1u
0s
1p
0o
1m
1l
0k
1e
1`
0\
0Z
0Y
0V
1U
0R
1Q
0N
1M
0J
1I
0F
1E
0B
1A
0>
1=
0:
19
11
bx W
bx (
#365000
1#
1/
#366000
0%
0)
0,
0X
0~
01
b110011001100110011001100110011 W
b110011001100110011001100110011 (
#370000
0#
0/
#375000
1#
1/
b1001 -
#380000
0#
0/
#385000
1#
1/
#390000
0#
0/
#395000
1#
1/
#400000
0#
0/
#405000
1#
1/
#410000
0#
0/
1%
b1001 &
b10011001100110011001100110011001 '
1V
0U
1S
1R
0Q
1O
1N
0M
1K
1J
0I
1G
1F
0E
1C
1B
0A
1?
1>
0=
1;
1:
09
17
11
04
13
bx W
bx (
#415000
1#
1/
#416000
0%
01
b10011001100110011001100110011001 W
b10011001100110011001100110011001 (
#420000
0#
0/
#425000
1#
1/
#430000
0#
0/
#435000
1#
1/
#440000
0#
0/
#445000
1#
1/
#450000
0#
0/
1%
b0 &
b11111010110011100000000000000000 '
0V
0S
0R
0O
0N
0K
0J
0G
0F
1E
1D
0B
1@
0>
1=
19
18
11
06
03
bx W
bx (
#455000
1#
1/
#456000
0%
01
b11111010110011100000000000000000 W
b11111010110011100000000000000000 (
#460000
0#
0/
#465000
1#
1/
#470000
0#
0/
1%
b1 &
b11111010110011100000000000000001 '
1V
11
16
bx W
bx (
#475000
1#
1/
#476000
0%
01
b11111010110011100000000000000001 W
b11111010110011100000000000000001 (
#480000
0#
0/
#485000
1#
1/
#490000
0#
0/
1%
b10 &
b11111010110011100000000000000010 '
0V
1U
11
06
15
bx W
bx (
#495000
1#
1/
#496000
0%
01
b11111010110011100000000000000010 W
b11111010110011100000000000000010 (
#500000
0#
0/
#505000
1#
1/
#510000
0#
0/
1%
b11 &
b11111010110011100000000000000011 '
1V
11
16
bx W
bx (
#515000
1#
1/
#516000
0%
01
b11111010110011100000000000000011 W
b11111010110011100000000000000011 (
#520000
0#
0/
#525000
1#
1/
#530000
0#
0/
1%
b100 &
b11111010110011100000000000000100 '
0V
0U
1T
11
06
05
14
bx W
bx (
#535000
1#
1/
#536000
0%
01
b11111010110011100000000000000100 W
b11111010110011100000000000000100 (
#540000
0#
0/
#545000
1#
1/
#550000
0#
0/
1%
b101 &
b11111010110011100000000000000101 '
1V
11
16
bx W
bx (
#555000
1#
1/
#556000
0%
01
b11111010110011100000000000000101 W
b11111010110011100000000000000101 (
#560000
0#
0/
#565000
1#
1/
#570000
0#
0/
1%
b110 &
b11111010110011100000000000000110 '
0V
1U
11
06
15
bx W
bx (
#575000
1#
1/
#576000
0%
01
b11111010110011100000000000000110 W
b11111010110011100000000000000110 (
#580000
0#
0/
#585000
1#
1/
#590000
0#
0/
1%
b111 &
b11111010110011100000000000000111 '
1V
11
16
bx W
bx (
#595000
1#
1/
#596000
0%
01
b11111010110011100000000000000111 W
b11111010110011100000000000000111 (
#600000
0#
0/
#605000
1#
1/
#610000
0#
0/
1%
b1000 &
b11111010110011100000000000001000 '
0V
0U
0T
1S
11
06
05
04
13
bx W
bx (
#615000
1#
1/
#616000
0%
01
b11111010110011100000000000001000 W
b11111010110011100000000000001000 (
#620000
0#
0/
#625000
1#
1/
#630000
0#
0/
1%
b1001 &
b11111010110011100000000000001001 '
1V
11
16
bx W
bx (
#635000
1#
1/
#636000
0%
01
b11111010110011100000000000001001 W
b11111010110011100000000000001001 (
#640000
0#
0/
#645000
1#
1/
#650000
0#
0/
1%
b1010 &
b11111010110011100000000000001010 '
0V
1U
11
06
15
bx W
bx (
#655000
1#
1/
#656000
0%
01
b11111010110011100000000000001010 W
b11111010110011100000000000001010 (
#660000
0#
0/
#665000
1#
1/
#670000
0#
0/
1%
b1011 &
b11111010110011100000000000001011 '
1V
11
16
bx W
bx (
#675000
1#
1/
#676000
0%
01
b11111010110011100000000000001011 W
b11111010110011100000000000001011 (
#680000
0#
0/
#685000
1#
1/
#690000
0#
0/
1%
b1100 &
b11111010110011100000000000001100 '
0V
0U
1T
11
06
05
14
bx W
bx (
#695000
1#
1/
#696000
0%
01
b11111010110011100000000000001100 W
b11111010110011100000000000001100 (
#700000
0#
0/
#705000
1#
1/
#710000
0#
0/
1%
b1101 &
b11111010110011100000000000001101 '
1V
11
16
bx W
bx (
#715000
1#
1/
#716000
0%
01
b11111010110011100000000000001101 W
b11111010110011100000000000001101 (
#720000
0#
0/
#725000
1#
1/
#730000
0#
0/
1%
b1110 &
b11111010110011100000000000001110 '
0V
1U
11
06
15
bx W
bx (
#735000
1#
1/
#736000
0%
01
b11111010110011100000000000001110 W
b11111010110011100000000000001110 (
#740000
0#
0/
#745000
1#
1/
#750000
0#
0/
1%
b1111 &
b11111010110011100000000000001111 '
1V
11
16
bx W
bx (
#755000
1#
1/
#756000
0%
01
b11111010110011100000000000001111 W
b11111010110011100000000000001111 (
#760000
0#
0/
#765000
1#
1/
#770000
0#
0/
1%
b10000 &
b11111010110011100000000000010000 '
0V
0U
0T
0S
1R
11
06
05
04
03
12
bx W
bx (
#775000
1#
1/
#776000
0%
01
b11111010110011100000000000010000 W
b11111010110011100000000000010000 (
#780000
0#
0/
#785000
1#
1/
#790000
0#
0/
1%
b10001 &
b11111010110011100000000000010001 '
1V
11
16
bx W
bx (
#795000
1#
1/
#796000
0%
01
b11111010110011100000000000010001 W
b11111010110011100000000000010001 (
#800000
0#
0/
#805000
1#
1/
#810000
0#
0/
1%
b10010 &
b11111010110011100000000000010010 '
0V
1U
11
06
15
bx W
bx (
#815000
1#
1/
#816000
0%
01
b11111010110011100000000000010010 W
b11111010110011100000000000010010 (
#820000
0#
0/
#825000
1#
1/
#830000
0#
0/
1%
b10011 &
b11111010110011100000000000010011 '
1V
11
16
bx W
bx (
#835000
1#
1/
#836000
0%
01
b11111010110011100000000000010011 W
b11111010110011100000000000010011 (
#840000
0#
0/
#845000
1#
1/
#850000
0#
0/
1%
b10100 &
b11111010110011100000000000010100 '
0V
0U
1T
11
06
05
14
bx W
bx (
#855000
1#
1/
#856000
0%
01
b11111010110011100000000000010100 W
b11111010110011100000000000010100 (
#860000
0#
0/
#865000
1#
1/
#870000
0#
0/
1%
b10101 &
b11111010110011100000000000010101 '
1V
11
16
bx W
bx (
#875000
1#
1/
#876000
0%
01
b11111010110011100000000000010101 W
b11111010110011100000000000010101 (
#880000
0#
0/
#885000
1#
1/
#890000
0#
0/
1%
b10110 &
b11111010110011100000000000010110 '
0V
1U
11
06
15
bx W
bx (
#895000
1#
1/
#896000
0%
01
b11111010110011100000000000010110 W
b11111010110011100000000000010110 (
#900000
0#
0/
#905000
1#
1/
#910000
0#
0/
1%
b10111 &
b11111010110011100000000000010111 '
1V
11
16
bx W
bx (
#915000
1#
1/
#916000
0%
01
b11111010110011100000000000010111 W
b11111010110011100000000000010111 (
#920000
0#
0/
#925000
1#
1/
#930000
0#
0/
1%
b11000 &
b11111010110011100000000000011000 '
0V
0U
0T
1S
11
06
05
04
13
bx W
bx (
#935000
1#
1/
#936000
0%
01
b11111010110011100000000000011000 W
b11111010110011100000000000011000 (
#940000
0#
0/
#945000
1#
1/
#950000
0#
0/
1%
b11001 &
b11111010110011100000000000011001 '
1V
11
16
bx W
bx (
#955000
1#
1/
#956000
0%
01
b11111010110011100000000000011001 W
b11111010110011100000000000011001 (
#960000
0#
0/
#965000
1#
1/
#970000
0#
0/
1%
b11010 &
b11111010110011100000000000011010 '
0V
1U
11
06
15
bx W
bx (
#975000
1#
1/
#976000
0%
01
b11111010110011100000000000011010 W
b11111010110011100000000000011010 (
#980000
0#
0/
#985000
1#
1/
#990000
0#
0/
1%
b11011 &
b11111010110011100000000000011011 '
1V
11
16
bx W
bx (
#995000
1#
1/
#996000
0%
01
b11111010110011100000000000011011 W
b11111010110011100000000000011011 (
#1000000
0#
0/
#1005000
1#
1/
#1010000
0#
0/
1%
b11100 &
b11111010110011100000000000011100 '
0V
0U
1T
11
06
05
14
bx W
bx (
#1015000
1#
1/
#1016000
0%
01
b11111010110011100000000000011100 W
b11111010110011100000000000011100 (
#1020000
0#
0/
#1025000
1#
1/
#1030000
0#
0/
1%
b11101 &
b11111010110011100000000000011101 '
1V
11
16
bx W
bx (
#1035000
1#
1/
#1036000
0%
01
b11111010110011100000000000011101 W
b11111010110011100000000000011101 (
#1040000
0#
0/
#1045000
1#
1/
#1050000
0#
0/
1%
b11110 &
b11111010110011100000000000011110 '
0V
1U
11
06
15
bx W
bx (
#1055000
1#
1/
#1056000
0%
01
b11111010110011100000000000011110 W
b11111010110011100000000000011110 (
#1060000
0#
0/
#1065000
1#
1/
#1070000
0#
0/
1%
b11111 &
b11111010110011100000000000011111 '
1V
11
16
bx W
bx (
#1075000
1#
1/
#1076000
0%
01
b11111010110011100000000000011111 W
b11111010110011100000000000011111 (
#1080000
0#
0/
#1085000
1#
1/
#1090000
0#
0/
b0 &
06
05
04
03
02
b11111010110011100000000000000000 W
b11111010110011100000000000000000 (
#1095000
1#
1/
b1010 -
#1100000
0#
0/
#1105000
1#
1/
#1110000
0#
0/
b1 &
16
b11111010110011100000000000000001 W
b11111010110011100000000000000001 (
#1115000
1#
1/
b1011 -
#1120000
0#
0/
#1125000
1#
1/
#1130000
0#
0/
b10 &
06
15
b11111010110011100000000000000010 W
b11111010110011100000000000000010 (
#1135000
1#
1/
b1100 -
#1140000
0#
0/
#1145000
1#
1/
#1150000
0#
0/
b11 &
16
b11111010110011100000000000000011 W
b11111010110011100000000000000011 (
#1155000
1#
1/
b1101 -
#1160000
0#
0/
#1165000
1#
1/
#1170000
0#
0/
b100 &
06
05
14
b11111010110011100000000000000100 W
b11111010110011100000000000000100 (
#1175000
1#
1/
b1110 -
#1180000
0#
0/
#1185000
1#
1/
#1190000
0#
0/
b101 &
16
b11111010110011100000000000000101 W
b11111010110011100000000000000101 (
#1195000
1#
1/
b1111 -
#1200000
0#
0/
#1205000
1#
1/
#1210000
0#
0/
b110 &
06
15
b11111010110011100000000000000110 W
b11111010110011100000000000000110 (
#1215000
1#
1/
b10000 -
#1220000
0#
0/
#1225000
1#
1/
#1230000
0#
0/
b111 &
16
b11111010110011100000000000000111 W
b11111010110011100000000000000111 (
#1235000
1#
1/
b10001 -
#1240000
0#
0/
#1245000
1#
1/
#1250000
0#
0/
b1000 &
06
05
04
13
b11111010110011100000000000001000 W
b11111010110011100000000000001000 (
#1255000
1#
1/
b10010 -
#1260000
0#
0/
#1265000
1#
1/
#1270000
0#
0/
b1001 &
16
b11111010110011100000000000001001 W
b11111010110011100000000000001001 (
#1275000
1#
1/
b10011 -
#1280000
0#
0/
#1285000
1#
1/
#1290000
0#
0/
b1010 &
06
15
b11111010110011100000000000001010 W
b11111010110011100000000000001010 (
#1295000
1#
1/
b10100 -
#1300000
0#
0/
#1305000
1#
1/
#1310000
0#
0/
b1011 &
16
b11111010110011100000000000001011 W
b11111010110011100000000000001011 (
#1315000
1#
1/
b10101 -
#1320000
0#
0/
#1325000
1#
1/
#1330000
0#
0/
b1100 &
06
05
14
b11111010110011100000000000001100 W
b11111010110011100000000000001100 (
#1335000
1#
1/
b10110 -
#1340000
0#
0/
#1345000
1#
1/
#1350000
0#
0/
b1101 &
16
b11111010110011100000000000001101 W
b11111010110011100000000000001101 (
#1355000
1#
1/
b10111 -
#1360000
0#
0/
#1365000
1#
1/
#1370000
0#
0/
b1110 &
06
15
b11111010110011100000000000001110 W
b11111010110011100000000000001110 (
#1375000
1#
1/
b11000 -
#1380000
0#
0/
#1385000
1#
1/
#1390000
0#
0/
b1111 &
16
b11111010110011100000000000001111 W
b11111010110011100000000000001111 (
#1395000
1#
1/
b11001 -
#1400000
0#
0/
#1405000
1#
1/
#1410000
0#
0/
b10000 &
06
05
04
03
12
b11111010110011100000000000010000 W
b11111010110011100000000000010000 (
#1415000
1#
1/
b11010 -
#1420000
0#
0/
#1425000
1#
1/
#1430000
0#
0/
b10001 &
16
b11111010110011100000000000010001 W
b11111010110011100000000000010001 (
#1435000
1#
1/
b11011 -
#1440000
0#
0/
#1445000
1#
1/
#1450000
0#
0/
b10010 &
06
15
b11111010110011100000000000010010 W
b11111010110011100000000000010010 (
#1455000
1#
1/
b11100 -
#1460000
0#
0/
#1465000
1#
1/
